cardiacctexplorer/cardiac_utils.py
cardiacctexplorer/fileconverter_utils.py
cardiacctexplorer/general_utils.py
cardiacctexplorer/io_utils.py
cardiacctexplorer/local_model.py
cardiacctexplorer/measurement_utils.py
cardiacctexplorer/nudf_laa_utils.py
cardiacctexplorer/nudf_predictor.py
cardiacctexplorer/python_api.py
cardiacctexplorer/segmentation_utils.py
cardiacctexplorer/surface_utils.py
cardiacctexplorer/totalsegmentator_utils.py
cardiacctexplorer/visualization_utils.py
cardiacctexplorer/bin/CardiacCTExplorer.py
cardiacctexplorer-0.1.0.dist-info/licenses/LICENSE
tests/test_cardiacctexplorer.py
cardiacctexplorer-0.1.0.dist-info/METADATA
cardiacctexplorer-0.1.0.dist-info/WHEEL
cardiacctexplorer-0.1.0.dist-info/entry_points.txt
cardiacctexplorer-0.1.0.dist-info/top_level.txt
cardiacctexplorer-0.1.0.dist-info/RECORD
