Metadata-Version: 2.4
Name: CardiacCTExplorer
Version: 0.1.0
Summary: CardiacCTExplorer can segment and analyse the human heart in CT scans.
Author-email: "Rasmus R. Paulsen" <rapa@dtu.dk>
License-Expression: MIT
Project-URL: homepage, https://github.com/RasmusRPaulsen/CardiacCTExplorer
Project-URL: repository, https://github.com/RasmusRPaulsen/CardiacCTExplorer
Keywords: deep learning,image segmentation,semantic segmentation,medical image analysis,medical image segmentation,Cardiac,CT
Classifier: Development Status :: 3 - Alpha
Classifier: Intended Audience :: Science/Research
Classifier: Programming Language :: Python :: 3
Classifier: Topic :: Scientific/Engineering :: Artificial Intelligence
Classifier: Topic :: Scientific/Engineering :: Image Recognition
Classifier: Topic :: Scientific/Engineering :: Medical Science Apps.
Requires-Python: >=3.9
License-File: LICENSE
Requires-Dist: TotalSegmentator
Requires-Dist: numpy
Requires-Dist: scipy
Requires-Dist: scikit-learn
Requires-Dist: scikit-image
Requires-Dist: SimpleITK
Requires-Dist: imageio
Requires-Dist: edt
Requires-Dist: vtk
Provides-Extra: dev
Requires-Dist: black; extra == "dev"
Requires-Dist: ruff; extra == "dev"
Requires-Dist: pre-commit; extra == "dev"
Dynamic: license-file
